AIRPALibrary/AIRPALibrary.py
AIRPALibrary/__init__.py
AIRPALibrary/function_timeout.py
AIRPALibrary/function_timeout_robot.py
AIRPALibrary-1.0.5.dist-info/METADATA
AIRPALibrary-1.0.5.dist-info/WHEEL
AIRPALibrary-1.0.5.dist-info/top_level.txt
AIRPALibrary-1.0.5.dist-info/RECORD
