Metadata-Version: 2.1
Name: AIRPALibrary
Version: 1.0.5
Summary: RPA Package for AI
Author: IT Dev HOTD Python Developer
Classifier: Programming Language :: Python :: 3
Classifier: License :: OSI Approved :: MIT License
Classifier: Operating System :: OS Independent
Requires-Python: >=3.7
